setup.py
knitpy/__init__.py
knitpy/documents.py
knitpy/engines.py
knitpy/knitpy.py
knitpy/knitpyapp.py
knitpy/utils.py
knitpy.egg-info/PKG-INFO
knitpy.egg-info/SOURCES.txt
knitpy.egg-info/dependency_links.txt
knitpy.egg-info/entry_points.txt
knitpy.egg-info/requires.txt
knitpy.egg-info/top_level.txt