Metadata-Version: 1.1
Name: knitpy
Version: 0.1.1
Summary: Elegant, flexible and fast dynamic report generation with python
Home-page: https://github.com/janschulz/knitpy/issues
Author: Jan Schulz
Author-email: jasc@gmx.net
License: BSD
Platform: UNKNOWN
Classifier: Development Status :: 4 - Beta
Classifier: Environment :: Console
Classifier: Intended Audience :: Developers
Classifier: Intended Audience :: End Users/Desktop
Classifier: Intended Audience :: Science/Research
Classifier: License :: OSI Approved :: BSD License
Classifier: Natural Language :: English
Classifier: Operating System :: OS Independent
Classifier: Programming Language :: Python
Classifier: Topic :: Scientific/Engineering :: Information Analysis
Classifier: Topic :: Utilities
